strong/__init__.py
strong/core/__init__.py
strong/core/decorators.py
strong/core/signature.py
strong/scripts/__init__.py
strong/scripts/strong.py
strong/utils/__init__.py
strong/utils/output.py
strong-0.2.2.dist-info/LICENSE.md
strong-0.2.2.dist-info/METADATA
strong-0.2.2.dist-info/WHEEL
strong-0.2.2.dist-info/entry_points.txt
strong-0.2.2.dist-info/top_level.txt
strong-0.2.2.dist-info/RECORD
