Metadata-Version: 2.1
Name: strong
Version: 0.2.2
Summary: Dynamic type checker for function signatures
Home-page: https://github.com/jeertmans/strong
Author: Jérome Eertmans
Author-email: jeertmans@icloud.com
License: MIT
Platform: UNKNOWN
Classifier: Programming Language :: Python :: 3
Classifier: License :: OSI Approved :: MIT License
Classifier: Operating System :: OS Independent
Requires-Python: >=3.8
